pycadet/CADET.hdf5
pycadet/DS9CADET.py
pycadet/__init__.py
pycadet/pycadet.py
pycadet-0.3.3.dist-info/licenses/LICENSE
pycadet-0.3.3.dist-info/METADATA
pycadet-0.3.3.dist-info/WHEEL
pycadet-0.3.3.dist-info/entry_points.txt
pycadet-0.3.3.dist-info/top_level.txt
pycadet-0.3.3.dist-info/RECORD
