Metadata-Version: 2.4
Name: pycadet
Version: 0.3.3
Summary: Cavity Detection Tool
Author-email: Tomas Plsek <plsek@physics.muni.cz>
License: MIT
Project-URL: Homepage, https://github.com/tomasplsek/CADET
Project-URL: Documentation, https://tomasplsek.github.io/CADET/
Project-URL: Repository, https://github.com/tomasplsek/CADET
Project-URL: Bug Tracker, https://github.com/tomasplsek/CADET/issues
Keywords: x-ray,cavity,detection,machine-learning,astronomy,chandra
Classifier: Development Status :: 4 - Beta
Classifier: Intended Audience :: Science/Research
Classifier: License :: OSI Approved :: MIT License
Classifier: Operating System :: OS Independent
Classifier: Programming Language :: Python :: 3
Classifier: Programming Language :: Python :: 3.8
Classifier: Programming Language :: Python :: 3.9
Classifier: Programming Language :: Python :: 3.10
Classifier: Programming Language :: Python :: 3.11
Classifier: Programming Language :: Python :: 3.12
Classifier: Topic :: Scientific/Engineering :: Astronomy
Classifier: Topic :: Scientific/Engineering :: Artificial Intelligence
Requires-Python: >=3.8
License-File: LICENSE
Requires-Dist: keras
Requires-Dist: scikit-learn
Requires-Dist: numpy>=1.8
Requires-Dist: pandas
Requires-Dist: matplotlib
Requires-Dist: astropy>=1.3
Requires-Dist: scipy>=0.14
Requires-Dist: pyds9
Provides-Extra: tensorflow
Requires-Dist: tensorflow; extra == "tensorflow"
Provides-Extra: pytorch
Requires-Dist: torch; extra == "pytorch"
Requires-Dist: torchvision; extra == "pytorch"
Provides-Extra: jax
Requires-Dist: jax; extra == "jax"
Requires-Dist: jaxlib; extra == "jax"
Provides-Extra: gpu-tensorflow
Requires-Dist: tensorflow[and-cuda]; extra == "gpu-tensorflow"
Provides-Extra: gpu-pytorch
Requires-Dist: torch[cuda]; extra == "gpu-pytorch"
Requires-Dist: torchvision; extra == "gpu-pytorch"
Provides-Extra: gpu-jax
Requires-Dist: jax[cuda12]; extra == "gpu-jax"
Provides-Extra: dev
Requires-Dist: pytest; extra == "dev"
Requires-Dist: pytest-cov; extra == "dev"
Requires-Dist: black; extra == "dev"
Requires-Dist: flake8; extra == "dev"
Requires-Dist: mypy; extra == "dev"
Dynamic: license-file
